setup.cfg
setup.py
bin/instantmusic
instantmusic/__init__.py
instantmusic.egg-info/PKG-INFO
instantmusic.egg-info/SOURCES.txt
instantmusic.egg-info/dependency_links.txt
instantmusic.egg-info/entry_points.txt
instantmusic.egg-info/not-zip-safe
instantmusic.egg-info/requires.txt
instantmusic.egg-info/top_level.txt