Metadata-Version: 1.0
Name: instantmusic
Version: 1.5
Summary: Instantly download any song! Without knowing the name of the song!!!!
Home-page: https://github.com/yask123/Instant-Music-Downloader
Author: Yask Srivastava
Author-email: yask123@gmail.com
License: MIT
Platform: UNKNOWN
